{
  "data": [
    {
      "type": "organization",
      "id": "1",
      "attributes": {
        "name": "Bay Bandits",
        "website": "https://bandits.run",
        "stravaId": "504077",
        "stravaHandle": "outlawed",
        "meetupId": null,
        "instagramHandle": "baybandits",
        "email": null,
        "phoneNumber": null,
        "descriptionHtml": "<h1 id=\"about-bay-bandits\" tabindex=\"-1\"><a class=\"header-anchor\" href=\"#about-bay-bandits\">#</a> About Bay Bandits</h1>\n<p>⛰ Trail Running Community 🏃‍♂️</p>\n<p>No dues. No singlets. Not a club.</p>\n<p>Come find your trail friends!</p>\n<p><em>ALL Runners Welcome</em></p>\n"
      },
      "relationships": {
        "runs": {
          "links": {
            "related": "/api/organization/1/runs.json"
          },
          "meta": {
            "count": 7
          }
        },
        "contacts": {
          "data": [
            {
              "type": "user",
              "id": "1"
            }
          ]
        }
      }
    },
    {
      "type": "organization",
      "id": "2",
      "attributes": {
        "name": "Beer Bucket Runners",
        "website": null,
        "stravaId": "1058474",
        "stravaHandle": "BeerBucketRun",
        "meetupId": null,
        "instagramHandle": "beer_bucket_run",
        "email": null,
        "phoneNumber": null,
        "descriptionHtml": "<p>The Beer Bucket Run (BBR) is a weekly trail run in the San Francisco Bay Area (East Bay, primarily).</p>\n<p>Our runs are always on trails and typically 12-14 miles. Runners of all ages and paces are 100 percent welcome and there is also always a shorter route. We recommend saving the route ahead of time.</p>\n<p>BBR is a great way to explore the amazing East Bay trails with a friendly group of runners. We meet every Sunday at 8-9 AM. The location changes each week, and we occasionally travel to other exotic locales (like Marin or the Sierra Foothills) when circumstances permit.</p>\n"
      },
      "relationships": {
        "runs": {
          "links": {
            "related": "/api/organization/2/runs.json"
          },
          "meta": {
            "count": 3
          }
        },
        "contacts": {
          "data": [
            {
              "type": "user",
              "id": "2"
            }
          ]
        }
      }
    },
    {
      "type": "organization",
      "id": "3",
      "attributes": {
        "name": "Salmon Run Club",
        "website": null,
        "stravaId": "963747",
        "stravaHandle": "salmon-run-club",
        "meetupId": null,
        "instagramHandle": "salmonrunclub",
        "email": null,
        "phoneNumber": null,
        "descriptionHtml": "<p>Salmon Run Club started in Summer 2021 as a followup to the Salomon Run Club and meets every Tuesday at 6:30pm at Skyline Gate Staging Area. We aim for 4-6 miles on the trails in Redwood, Sibley, and Joaquin Miller with new routes each week to see all the lovely trails in our backyard (within the limits of an evening trail run). Afterwards we hangout and eat snacks.</p>\n<p>There are usually a few pace groups but if you’re unfamiliar with the area we recommend you download the route beforehand and since it’s getting dark earlier please bring a headlamp!</p>\n<p>“We sometimes run up stream”</p>\n"
      },
      "relationships": {
        "runs": {
          "links": {
            "related": "/api/organization/3/runs.json"
          },
          "meta": {
            "count": 1
          }
        },
        "contacts": {
          "data": [
            {
              "type": "user",
              "id": "4"
            }
          ]
        }
      }
    },
    {
      "type": "organization",
      "id": "4",
      "attributes": {
        "name": "Berkeley Run Club",
        "website": null,
        "stravaId": "25365",
        "stravaHandle": "berkeley-running-club",
        "meetupId": "runbrc",
        "instagramHandle": null,
        "email": null,
        "phoneNumber": null,
        "descriptionHtml": "<p>Come out and meet other local runners for great camaraderie and motivation. Some of us jog, some of us run, some of us race, but we all have fun! The key is to show up and give it a try – the sooner you come out and join us, the sooner you will be on the road to fitness, health, and meeting lifelong running friends!</p>\n"
      },
      "relationships": {
        "runs": {
          "links": {
            "related": "/api/organization/4/runs.json"
          },
          "meta": {
            "count": 1
          }
        },
        "contacts": {
          "data": [
            {
              "type": "user",
              "id": "3"
            }
          ]
        }
      }
    },
    {
      "type": "organization",
      "id": "5",
      "attributes": {
        "name": "San Francisco Running Company",
        "website": "https://www.sfrunco.com/about-us/weeklyruns/",
        "stravaId": "15879",
        "stravaHandle": "san-francisco-running-company",
        "meetupId": null,
        "instagramHandle": "sfrunco",
        "email": null,
        "phoneNumber": null,
        "descriptionHtml": null
      },
      "relationships": {
        "runs": {
          "links": {
            "related": "/api/organization/5/runs.json"
          },
          "meta": {
            "count": 3
          }
        },
        "contacts": {
          "data": [
            {
              "type": "user",
              "id": "8"
            }
          ]
        }
      }
    },
    {
      "type": "organization",
      "id": "6",
      "attributes": {
        "name": "Marin Run Club",
        "website": "https://marinrunningclub.com",
        "stravaId": "191891",
        "stravaHandle": "marin-run-club",
        "meetupId": "marin-running-club",
        "instagramHandle": null,
        "email": null,
        "phoneNumber": null,
        "descriptionHtml": "<p>Join us for trail and road runs in Marin County.</p>\n"
      },
      "relationships": {
        "runs": {
          "links": {
            "related": "/api/organization/6/runs.json"
          },
          "meta": {
            "count": 2
          }
        },
        "contacts": {
          "data": [
            {
              "type": "user",
              "id": "9"
            }
          ]
        }
      }
    }
  ],
  "included": [
    {
      "type": "user",
      "id": "1",
      "attributes": {
        "firstName": "Chris",
        "lastName": "Thoburn",
        "email": "runspired@gmail.com",
        "phoneNumber": "17138983236",
        "hasWhatsApp": true,
        "stravaId": "runspired",
        "instagramHandle": "runspired",
        "descriptionHtml": null
      }
    },
    {
      "type": "user",
      "id": "2",
      "attributes": {
        "firstName": "Karen",
        "lastName": "Barnes",
        "email": null,
        "phoneNumber": null,
        "hasWhatsApp": true,
        "stravaId": "97687403",
        "instagramHandle": "traillove_kb",
        "descriptionHtml": null
      }
    },
    {
      "type": "user",
      "id": "4",
      "attributes": {
        "firstName": "Tom",
        "lastName": "Stitt",
        "email": null,
        "phoneNumber": null,
        "hasWhatsApp": true,
        "stravaId": "2175208",
        "instagramHandle": "thomasstitt",
        "descriptionHtml": null
      }
    },
    {
      "type": "user",
      "id": "3",
      "attributes": {
        "firstName": "Edward",
        "lastName": "Holets",
        "email": null,
        "phoneNumber": null,
        "hasWhatsApp": true,
        "stravaId": "12268454",
        "instagramHandle": "nedword",
        "descriptionHtml": null
      }
    },
    {
      "type": "user",
      "id": "8",
      "attributes": {
        "firstName": "Jojo",
        "lastName": "Roldan",
        "email": null,
        "phoneNumber": null,
        "hasWhatsApp": true,
        "stravaId": "2860482",
        "instagramHandle": "from_here_we_go",
        "descriptionHtml": null
      }
    },
    {
      "type": "user",
      "id": "9",
      "attributes": {
        "firstName": "Dan",
        "lastName": "Pagano",
        "email": null,
        "phoneNumber": null,
        "hasWhatsApp": true,
        "stravaId": "309460",
        "instagramHandle": "dans_wildlife",
        "descriptionHtml": null
      }
    }
  ]
}