{
  "data": [
    {
      "type": "organization",
      "id": "1",
      "attributes": {
        "name": "Bay Bandits",
        "website": "https://bandits.run",
        "stravaId": "504077",
        "stravaHandle": "outlawed",
        "meetupId": null,
        "instagramHandle": "baybandits",
        "email": null,
        "phoneNumber": null,
        "descriptionHtml": "<h1 id=\"about-bay-bandits\" tabindex=\"-1\"><a class=\"header-anchor\" href=\"#about-bay-bandits\">#</a> About Bay Bandits</h1>\n<p>⛰ Trail Running Community 🏃‍♂️</p>\n<p>No dues. No singlets. Not a club.</p>\n<p>Come find your trail friends!</p>\n<p><em>ALL Runners Welcome</em></p>\n"
      },
      "relationships": {
        "runs": {
          "links": {
            "related": "/api/organization/1/runs.json"
          },
          "meta": {
            "count": 7
          }
        },
        "contacts": {
          "data": [
            {
              "type": "user",
              "id": "1"
            }
          ]
        }
      }
    },
    {
      "type": "organization",
      "id": "2",
      "attributes": {
        "name": "Beer Bucket Runners",
        "website": null,
        "stravaId": "1058474",
        "stravaHandle": "BeerBucketRun",
        "meetupId": null,
        "instagramHandle": "beer_bucket_run",
        "email": null,
        "phoneNumber": null,
        "descriptionHtml": null
      },
      "relationships": {
        "runs": {
          "links": {
            "related": "/api/organization/2/runs.json"
          },
          "meta": {
            "count": 3
          }
        },
        "contacts": {
          "data": [
            {
              "type": "user",
              "id": "2"
            }
          ]
        }
      }
    },
    {
      "type": "organization",
      "id": "3",
      "attributes": {
        "name": "Salmon Run Club",
        "website": null,
        "stravaId": "963747",
        "stravaHandle": "salmon-run-club",
        "meetupId": null,
        "instagramHandle": "salmonrunclub",
        "email": null,
        "phoneNumber": null,
        "descriptionHtml": null
      },
      "relationships": {
        "runs": {
          "links": {
            "related": "/api/organization/3/runs.json"
          },
          "meta": {
            "count": 1
          }
        },
        "contacts": {
          "data": [
            {
              "type": "user",
              "id": "4"
            }
          ]
        }
      }
    },
    {
      "type": "organization",
      "id": "4",
      "attributes": {
        "name": "Berkeley Run Club",
        "website": null,
        "stravaId": "25365",
        "stravaHandle": "berkeley-running-club",
        "meetupId": "runbrc",
        "instagramHandle": null,
        "email": null,
        "phoneNumber": null,
        "descriptionHtml": null
      },
      "relationships": {
        "runs": {
          "links": {
            "related": "/api/organization/4/runs.json"
          },
          "meta": {
            "count": 1
          }
        },
        "contacts": {
          "data": [
            {
              "type": "user",
              "id": "3"
            }
          ]
        }
      }
    },
    {
      "type": "organization",
      "id": "5",
      "attributes": {
        "name": "San Francisco Running Company",
        "website": "https://www.sfrunco.com/about-us/weeklyruns/",
        "stravaId": "15879",
        "stravaHandle": "san-francisco-running-company",
        "meetupId": null,
        "instagramHandle": "sfrunco",
        "email": null,
        "phoneNumber": null,
        "descriptionHtml": null
      },
      "relationships": {
        "runs": {
          "links": {
            "related": "/api/organization/5/runs.json"
          },
          "meta": {
            "count": 3
          }
        },
        "contacts": {
          "data": [
            {
              "type": "user",
              "id": "8"
            }
          ]
        }
      }
    },
    {
      "type": "organization",
      "id": "6",
      "attributes": {
        "name": "Marin Run Club",
        "website": "https://marinrunningclub.com",
        "stravaId": "191891",
        "stravaHandle": "marin-run-club",
        "meetupId": "marin-running-club",
        "instagramHandle": null,
        "email": null,
        "phoneNumber": null,
        "descriptionHtml": null
      },
      "relationships": {
        "runs": {
          "links": {
            "related": "/api/organization/6/runs.json"
          },
          "meta": {
            "count": 2
          }
        },
        "contacts": {
          "data": [
            {
              "type": "user",
              "id": "9"
            }
          ]
        }
      }
    }
  ],
  "included": [
    {
      "type": "user",
      "id": "1",
      "attributes": {
        "firstName": "Chris",
        "lastName": "Thoburn",
        "email": "runspired@gmail.com",
        "phoneNumber": "17138983236",
        "hasWhatsApp": true,
        "stravaId": "runspired",
        "instagramHandle": "runspired",
        "descriptionHtml": null
      }
    },
    {
      "type": "user",
      "id": "2",
      "attributes": {
        "firstName": "Karen",
        "lastName": "Barnes",
        "email": null,
        "phoneNumber": null,
        "hasWhatsApp": true,
        "stravaId": "97687403",
        "instagramHandle": "traillove_kb",
        "descriptionHtml": null
      }
    },
    {
      "type": "user",
      "id": "4",
      "attributes": {
        "firstName": "Tom",
        "lastName": "Stitt",
        "email": null,
        "phoneNumber": null,
        "hasWhatsApp": true,
        "stravaId": "2175208",
        "instagramHandle": "thomasstitt",
        "descriptionHtml": null
      }
    },
    {
      "type": "user",
      "id": "3",
      "attributes": {
        "firstName": "Edward",
        "lastName": "Holets",
        "email": null,
        "phoneNumber": null,
        "hasWhatsApp": true,
        "stravaId": "12268454",
        "instagramHandle": "nedword",
        "descriptionHtml": null
      }
    },
    {
      "type": "user",
      "id": "8",
      "attributes": {
        "firstName": "Jojo",
        "lastName": "Roldan",
        "email": null,
        "phoneNumber": null,
        "hasWhatsApp": true,
        "stravaId": "2860482",
        "instagramHandle": "from_here_we_go",
        "descriptionHtml": null
      }
    },
    {
      "type": "user",
      "id": "9",
      "attributes": {
        "firstName": "Dan",
        "lastName": "Pagano",
        "email": null,
        "phoneNumber": null,
        "hasWhatsApp": true,
        "stravaId": "309460",
        "instagramHandle": "dans_wildlife",
        "descriptionHtml": null
      }
    }
  ]
}